qsharp-1.25.1.dist-info/METADATA
qsharp-1.25.1.dist-info/WHEEL
qsharp/.data/qsharp_codemirror.js
qsharp/__init__.py
qsharp/_device/__init__.py
qsharp/_device/_atom/__init__.py
qsharp/_device/_atom/_decomp.py
qsharp/_device/_atom/_optimize.py
qsharp/_device/_atom/_reorder.py
qsharp/_device/_atom/_scheduler.py
qsharp/_device/_atom/_trace.py
qsharp/_device/_atom/_utils.py
qsharp/_device/_atom/_validate.py
qsharp/_device/_device.py
qsharp/_fs.py
qsharp/_http.py
qsharp/_ipython.py
qsharp/_native.abi3.so
qsharp/_native.pyi
qsharp/_qsharp.py
qsharp/_simulation.py
qsharp/code/__init__.py
qsharp/code/__init__.pyi
qsharp/estimator/__init__.py
qsharp/estimator/_estimator.py
qsharp/interop/__init__.py
qsharp/interop/qiskit/__init__.py
qsharp/interop/qiskit/backends/__init__.py
qsharp/interop/qiskit/backends/backend_base.py
qsharp/interop/qiskit/backends/compilation.py
qsharp/interop/qiskit/backends/errors.py
qsharp/interop/qiskit/backends/qirtarget.py
qsharp/interop/qiskit/backends/qsharp_backend.py
qsharp/interop/qiskit/backends/re_backend.py
qsharp/interop/qiskit/execution/__init__.py
qsharp/interop/qiskit/execution/default.py
qsharp/interop/qiskit/jobs/__init__.py
qsharp/interop/qiskit/jobs/qsjob.py
qsharp/interop/qiskit/jobs/qsjobset.py
qsharp/interop/qiskit/passes/__init__.py
qsharp/interop/qiskit/passes/remove_delay.py
qsharp/noisy_simulator/__init__.py
qsharp/noisy_simulator/_noisy_simulator.py
qsharp/noisy_simulator/_noisy_simulator.pyi
qsharp/openqasm/__init__.py
qsharp/openqasm/_circuit.py
qsharp/openqasm/_compile.py
qsharp/openqasm/_estimate.py
qsharp/openqasm/_import.py
qsharp/openqasm/_ipython.py
qsharp/openqasm/_run.py
qsharp/openqasm/_utils.py
qsharp/telemetry.py
qsharp/telemetry_events.py
qsharp/utils/__init__.py
qsharp/utils/_utils.py
qsharp-1.25.1.dist-info/RECORD
