Metadata-Version: 2.4
Name: qsharp
Version: 1.25.1
Classifier: License :: OSI Approved :: MIT License
Classifier: Development Status :: 5 - Production/Stable
Classifier: Intended Audience :: Developers
Classifier: Programming Language :: Python :: 3
Classifier: Programming Language :: Python :: 3.10
Classifier: Programming Language :: Python :: 3.11
Classifier: Programming Language :: Python :: 3.12
Classifier: Programming Language :: Python :: 3.13
Classifier: Programming Language :: Python
Classifier: Programming Language :: Rust
Classifier: Operating System :: MacOS
Classifier: Operating System :: Microsoft :: Windows
Classifier: Operating System :: POSIX :: Linux
Requires-Dist: qsharp-jupyterlab ; extra == 'jupyterlab'
Requires-Dist: qsharp-widgets ; extra == 'widgets'
Requires-Dist: qiskit>=1.2.2,<3.0.0 ; extra == 'qiskit'
Provides-Extra: jupyterlab
Provides-Extra: widgets
Provides-Extra: qiskit
Summary: Q# Python Bindings
Home-Page: https://github.com/microsoft/qsharp
Author: Microsoft
License: MIT
Requires-Python: >=3.10
Project-URL: Source Code, https://github.com/microsoft/qsharp
